cellmaps_ppi_embedding/__init__.py
cellmaps_ppi_embedding/cellmaps_ppi_embeddingcmd.py
cellmaps_ppi_embedding/exceptions.py
cellmaps_ppi_embedding/readme_outputs.txt
cellmaps_ppi_embedding/runner.py
cellmaps_ppi_embedding-0.4.3.data/scripts/cellmaps_ppi_embeddingcmd.py
cellmaps_ppi_embedding-0.4.3.dist-info/AUTHORS.rst
cellmaps_ppi_embedding-0.4.3.dist-info/LICENSE
cellmaps_ppi_embedding-0.4.3.dist-info/METADATA
cellmaps_ppi_embedding-0.4.3.dist-info/WHEEL
cellmaps_ppi_embedding-0.4.3.dist-info/top_level.txt
cellmaps_ppi_embedding-0.4.3.dist-info/RECORD
