Metadata-Version: 2.1
Name: cellmaps_ppi_embedding
Version: 0.4.3
Summary: A tool to generate embeddings from networks
Home-page: https://github.com/idekerlab/cellmaps_ppi_embedding
Author: Cell Maps team
Author-email: tools@cm4ai.org
License: MIT license
Keywords: cellmaps_ppi_embedding
Classifier: Development Status :: 2 - Pre-Alpha
Classifier: Intended Audience :: Developers
Classifier: License :: OSI Approved :: MIT License
Classifier: Natural Language :: English
Classifier: Programming Language :: Python :: 3.8
Classifier: Programming Language :: Python :: 3.9
Classifier: Programming Language :: Python :: 3.10
Classifier: Programming Language :: Python :: 3.11
License-File: LICENSE
License-File: AUTHORS.rst
Requires-Dist: scipy <1.13,>=1.10.1
Requires-Dist: cellmaps-utils <1.0.0,>=0.4.0
Requires-Dist: node2vec <0.5.0,>=0.4.6
Requires-Dist: networkx <2.9,>=2.8
